decorator_args.py
decorator_args-1.1.dist-info/DESCRIPTION.rst
decorator_args-1.1.dist-info/METADATA
decorator_args-1.1.dist-info/RECORD
decorator_args-1.1.dist-info/WHEEL
decorator_args-1.1.dist-info/metadata.json
decorator_args-1.1.dist-info/top_level.txt
