Metadata-Version: 2.0
Name: decorator-args
Version: 1.1
Summary: Optional/required/keyword-only decorator arguments made easy.
Home-page: https://github.com/pasztorpisti/decorator-args
Author: István Pásztor
Author-email: pasztorpisti@gmail.com
License: MIT
Keywords: optional required keyword only decorator arguments args
Platform: UNKNOWN
Classifier: License :: OSI Approved :: MIT License
Classifier: Development Status :: 5 - Production/Stable
Classifier: Intended Audience :: Developers
Classifier: Topic :: Software Development :: Libraries :: Python Modules
Classifier: Programming Language :: Python :: 2
Classifier: Programming Language :: Python :: 3
Classifier: Programming Language :: Python :: Implementation :: CPython
Classifier: Programming Language :: Python :: Implementation :: PyPy
